fridafuse/__about__.py
fridafuse/__init__.py
fridafuse/apk_utils.py
fridafuse/cli.py
fridafuse/constants.py
fridafuse/downloader.py
fridafuse/elf_reader.py
fridafuse/manifest_utils.py
fridafuse/patcher.py
fridafuse/utils.py
fridafuse/commands/__init__.py
fridafuse/commands/auto.py
fridafuse/commands/native_lib.py
fridafuse/commands/smali.py
fridafuse-0.3.0.dist-info/METADATA
fridafuse-0.3.0.dist-info/WHEEL
fridafuse-0.3.0.dist-info/entry_points.txt
fridafuse-0.3.0.dist-info/licenses/LICENSE
fridafuse-0.3.0.dist-info/RECORD
