Metadata-Version: 2.4
Name: fridafuse
Version: 0.3.0
Summary: Automatically patch APK with frida-gadget into Smali or Native Library.
Project-URL: Documentation, https://github.com/eriestrisnadi/fridafuse#table-of-contents
Project-URL: Issues, https://github.com/eriestrisnadi/fridafuse/issues
Project-URL: Source, https://github.com/eriestrisnadi/fridafuse
Author-email: Eries Trisnadi <lognus21@gmail.com>
License: GPL-3.0
License-File: LICENSE
Classifier: Environment :: Console
Classifier: Intended Audience :: Developers
Classifier: Intended Audience :: Science/Research
Classifier: License :: OSI Approved :: GNU General Public License v3 or later (GPLv3+)
Classifier: Operating System :: MacOS :: MacOS X
Classifier: Operating System :: Microsoft :: Windows
Classifier: Operating System :: POSIX :: Linux
Classifier: Programming Language :: Python :: 3
Classifier: Programming Language :: Python :: 3.8
Classifier: Programming Language :: Python :: 3.9
Classifier: Programming Language :: Python :: 3.10
Classifier: Topic :: Software Development :: Debuggers
Requires-Python: >=3.8
Requires-Dist: click>=8.1.8
Requires-Dist: defusedxml>=0.7.0
Requires-Dist: inquirer>=3.4.0
Requires-Dist: lief>=0.16.0
Requires-Dist: pyyaml~=6.0
Requires-Dist: requests>=2.32.2
